ids_peak_icv/__init__.py
ids_peak_icv/exceptions.py
ids_peak_icv/libids_peak_icv.so
ids_peak_icv/libtbb_libcxx.so.12
ids_peak_icv/py.typed
ids_peak_icv/backend/__init__.py
ids_peak_icv/backend/datatypes.py
ids_peak_icv/backend/utils.py
ids_peak_icv/calibration/__init__.py
ids_peak_icv/calibration/calibration_parameters.py
ids_peak_icv/calibration/calibration_plate.py
ids_peak_icv/calibration/calibration_result.py
ids_peak_icv/calibration/calibration_view.py
ids_peak_icv/calibration/camera_calibration.py
ids_peak_icv/calibration/extrinsic_parameters.py
ids_peak_icv/calibration/intrinsic_parameters.py
ids_peak_icv/calibration/reprojection_error.py
ids_peak_icv/calibration/workspace_calibration.py
ids_peak_icv/datatypes/__init__.py
ids_peak_icv/datatypes/binning_factor.py
ids_peak_icv/datatypes/image.py
ids_peak_icv/datatypes/point_cloud.py
ids_peak_icv/datatypes/region.py
ids_peak_icv/datatypes/rotation_angle.py
ids_peak_icv/datatypes/undistorted_image.py
ids_peak_icv/datatypes/xyz_image.py
ids_peak_icv/datatypes/geometry/__init__.py
ids_peak_icv/datatypes/geometry/coordinate_system.py
ids_peak_icv/datatypes/geometry/point_xyz.py
ids_peak_icv/datatypes/geometry/point_xyzi.py
ids_peak_icv/datatypes/geometry/polygon.py
ids_peak_icv/filters/__init__.py
ids_peak_icv/filters/median_filter.py
ids_peak_icv/painting/__init__.py
ids_peak_icv/painting/color.py
ids_peak_icv/painting/drawable.py
ids_peak_icv/painting/drawing_options.py
ids_peak_icv/painting/opacity.py
ids_peak_icv/painting/painter.py
ids_peak_icv/pipeline/__init__.py
ids_peak_icv/pipeline/default_pipeline.py
ids_peak_icv/pipeline/processing_policy.py
ids_peak_icv/pipeline/_internal/__init__.py
ids_peak_icv/pipeline/_internal/color_matrix_transformation_module.py
ids_peak_icv/pipeline/_internal/debayer_channel_layout.py
ids_peak_icv/pipeline/_internal/debayer_conversion_policy.py
ids_peak_icv/pipeline/_internal/debayer_module.py
ids_peak_icv/pipeline/_internal/downsampling_module.py
ids_peak_icv-1.1.0.6615.dist-info/licenses/LICENSE
ids_peak_icv-1.1.0.6615.dist-info/licenses/third_party_copyrights.txt
ids_peak_icv-1.1.0.6615.dist-info/licenses/third_party_licenses.txt
ids_peak_icv-1.1.0.6615.dist-info/METADATA
ids_peak_icv-1.1.0.6615.dist-info/WHEEL
ids_peak_icv-1.1.0.6615.dist-info/top_level.txt
ids_peak_icv-1.1.0.6615.dist-info/RECORD
