Metadata-Version: 2.4
Name: ids_peak_icv
Version: 1.1.0.6615
Summary: ids_peak_icv - A library for image computer vision
Author-email: IDS Imaging Development Systems GmbH <support@ids-imaging.com>
Project-URL: Homepage, https://www.ids-imaging.com
Platform: manylinux_2_27_aarch64
Classifier: Programming Language :: Python :: 3
Classifier: Topic :: Multimedia :: Graphics :: Capture :: Digital Camera
Classifier: Topic :: Scientific/Engineering :: Image Processing
Classifier: Typing :: Typed
Requires-Python: >=3.10
License-File: LICENSE
License-File: third_party_copyrights.txt
License-File: third_party_licenses.txt
Requires-Dist: numpy
Requires-Dist: ids-peak-ipl>=1.17.1.0
Requires-Dist: ids-peak-common>=1.1.0.0
Dynamic: license-file
